promptliy/__init__.py
promptliy/client.py
promptliy-1.0.2.dist-info/licenses/LICENSE
promptliy-1.0.2.dist-info/METADATA
promptliy-1.0.2.dist-info/WHEEL
promptliy-1.0.2.dist-info/top_level.txt
promptliy-1.0.2.dist-info/RECORD
