Metadata-Version: 2.4
Name: promptliy
Version: 1.0.2
Summary: Promptliy SDK for accessing Promptliy API
Author-email: Promptliy Inc <support@promptliy.ai>
License: Promptliy SDK License
Project-URL: Homepage, https://promptliy.ai
Keywords: promptliy,prompts,api,client,sdk,ai,python
Requires-Python: >=3.7
License-File: LICENSE
Requires-Dist: requests>=2.25.0
Provides-Extra: cache
Requires-Dist: cachetools>=5.3.0; extra == "cache"
Dynamic: license-file
